VimCongRumenDaoJingtongFix1/README.md
VimCongRumenDaoJingtongFix1/__init__.py
VimCongRumenDaoJingtongFix1/__main__.py
VimCongRumenDaoJingtongFix1/file.epub
VimCongRumenDaoJingtongFix1/index.html
VimCongRumenDaoJingtongFix1/css/__init__.py
VimCongRumenDaoJingtongFix1/css/annotations.css
VimCongRumenDaoJingtongFix1/css/main.css
VimCongRumenDaoJingtongFix1/css/normalize.css
VimCongRumenDaoJingtongFix1/css/popup.css
VimCongRumenDaoJingtongFix1/font/__init__.py
VimCongRumenDaoJingtongFix1/font/fontello.eot
VimCongRumenDaoJingtongFix1/font/fontello.svg
VimCongRumenDaoJingtongFix1/font/fontello.ttf
VimCongRumenDaoJingtongFix1/font/fontello.woff
VimCongRumenDaoJingtongFix1/img/__init__.py
VimCongRumenDaoJingtongFix1/img/annotator-glyph-sprite.png
VimCongRumenDaoJingtongFix1/img/annotator-icon-sprite.png
VimCongRumenDaoJingtongFix1/img/apple-touch-icon.png
VimCongRumenDaoJingtongFix1/img/cancelfullscreen.png
VimCongRumenDaoJingtongFix1/img/close.png
VimCongRumenDaoJingtongFix1/img/fullscreen.png
VimCongRumenDaoJingtongFix1/img/loader.gif
VimCongRumenDaoJingtongFix1/img/menu-icon.png
VimCongRumenDaoJingtongFix1/img/save.png
VimCongRumenDaoJingtongFix1/img/saved.png
VimCongRumenDaoJingtongFix1/img/settings-s.png
VimCongRumenDaoJingtongFix1/img/settings.png
VimCongRumenDaoJingtongFix1/img/star.png
VimCongRumenDaoJingtongFix1/js/__init__.py
VimCongRumenDaoJingtongFix1/js/epub.js
VimCongRumenDaoJingtongFix1/js/epub.min.js
VimCongRumenDaoJingtongFix1/js/epub.min.map
VimCongRumenDaoJingtongFix1/js/hooks.min.js
VimCongRumenDaoJingtongFix1/js/hooks.min.map
VimCongRumenDaoJingtongFix1/js/reader.js
VimCongRumenDaoJingtongFix1/js/reader.js.map
VimCongRumenDaoJingtongFix1/js/reader.min.js
VimCongRumenDaoJingtongFix1/js/reader.min.map
VimCongRumenDaoJingtongFix1/js/hooks/__init__.py
VimCongRumenDaoJingtongFix1/js/hooks/extensions/__init__.py
VimCongRumenDaoJingtongFix1/js/hooks/extensions/highlight.js
VimCongRumenDaoJingtongFix1/js/libs/__init__.py
vim_cong_rumen_dao_jingtong_fix1-2025.3.25.0.dist-info/METADATA
vim_cong_rumen_dao_jingtong_fix1-2025.3.25.0.dist-info/WHEEL
vim_cong_rumen_dao_jingtong_fix1-2025.3.25.0.dist-info/entry_points.txt
vim_cong_rumen_dao_jingtong_fix1-2025.3.25.0.dist-info/top_level.txt
vim_cong_rumen_dao_jingtong_fix1-2025.3.25.0.dist-info/RECORD
